pyinsights/__init__.py
pyinsights/__version__.py
pyinsights/cli/__init__.py
pyinsights/cli/formatter.py
pyinsights/cli/options.py
pyinsights/cli/writer.py
pyinsights/config.py
pyinsights/exceptions.py
pyinsights/helper.py
pyinsights/progress.py
pyinsights/pyinsights.py
pyinsights/query.py
pyinsights/schema/version_1.0.json
pyinsights-0.4.2.dist-info/entry_points.txt
pyinsights-0.4.2.dist-info/LICENSE
pyinsights-0.4.2.dist-info/WHEEL
pyinsights-0.4.2.dist-info/METADATA
pyinsights-0.4.2.dist-info/RECORD
