Metadata-Version: 2.1
Name: pyinsights
Version: 0.4.2
Summary: AWS CloudWatch Logs Insights is wrapped by Python
Home-page: https://github.com/homoluctus/pyinsights
License: MIT
Keywords: aws,insights,cli
Author: homoluctus
Author-email: w.slife18sy@gmail.com
Requires-Python: >=3.8,<4.0
Classifier: License :: OSI Approved :: MIT License
Classifier: Programming Language :: Python :: 3
Classifier: Programming Language :: Python :: 3.8
Requires-Dist: boto3 (>=1.10.45,<2.0.0)
Requires-Dist: jsonschema (>=3.2.0,<4.0.0)
Requires-Dist: pyyaml (>=5.2,<6.0)
Project-URL: Repository, https://github.com/homoluctus/pyinsights
